[
  {
    "date": "2026-03-31T05:28:02Z",
    "commit": "32476d5",
    "run_number": 1,
    "run_url": "https://github.com/yito88/nebel/actions/runs/23781672797",
    "ann_recall": 0.973,
    "passed": true
  },
  {
    "date": "2026-04-01T05:40:09Z",
    "commit": "fdcb383",
    "run_number": 2,
    "run_url": "https://github.com/yito88/nebel/actions/runs/23833513487",
    "ann_recall": 0.974,
    "passed": true
  },
  {
    "date": "2026-04-02T05:20:31Z",
    "commit": "8a96306",
    "run_number": 3,
    "run_url": "https://github.com/yito88/nebel/actions/runs/23884924399",
    "ann_recall": 0.965,
    "passed": true
  }
]